nbdev_template/__init__.py
nbdev_template/_modidx.py
nbdev_template/card.py
nbdev_template/deck.py
test_nbdev_py-0.0.9.dist-info/LICENSE
test_nbdev_py-0.0.9.dist-info/METADATA
test_nbdev_py-0.0.9.dist-info/WHEEL
test_nbdev_py-0.0.9.dist-info/entry_points.txt
test_nbdev_py-0.0.9.dist-info/top_level.txt
test_nbdev_py-0.0.9.dist-info/RECORD
